temimbo/__init__.py
temimbo/dataclasses.py
temimbo-0.1.2.dist-info/LICENSE
temimbo-0.1.2.dist-info/METADATA
temimbo-0.1.2.dist-info/WHEEL
temimbo-0.1.2.dist-info/top_level.txt
temimbo-0.1.2.dist-info/RECORD
