Metadata-Version: 2.1
Name: temimbo
Version: 0.1.2
Summary: Temimbo: A library for Enhanced Personalized Language Learning
Author-email: Franziska Penzkofer <franziska@lammelhoefl.de>
License: MIT License
Project-URL: repository, https://github.com/F-penzkofer/LanguageTeacher
Project-URL: documentation, https://github.com/F-penzkofer/LanguageTeacher
Keywords: language learning,adaptive learning
Classifier: License :: OSI Approved :: MIT License
Classifier: Programming Language :: Python
Classifier: Programming Language :: Python :: 3
Requires-Python: >=3.9
License-File: LICENSE
Requires-Dist: requests >=2.31.0
Requires-Dist: openai
Requires-Dist: pydantic ==1.10.2
Provides-Extra: build
Requires-Dist: build ; extra == 'build'
Requires-Dist: twine ; extra == 'build'
Provides-Extra: dev
Requires-Dist: python-dotenv ; extra == 'dev'
